pefile.py
peutils.py
ordlookup/__init__.py
ordlookup/oleaut32.py
ordlookup/ws2_32.py
pefile_fork-2020.12.16.dist-info/LICENSE
pefile_fork-2020.12.16.dist-info/METADATA
pefile_fork-2020.12.16.dist-info/WHEEL
pefile_fork-2020.12.16.dist-info/top_level.txt
pefile_fork-2020.12.16.dist-info/RECORD
