Metadata-Version: 2.1
Name: pefile-fork
Version: 2020.12.16
Summary: Python PE parsing module
Home-page: https://github.com/mlodic/pefile
Author: Ero Carrera
Author-email: ero.carrera@gmail.com
License: UNKNOWN
Keywords: pe,exe,dll,pefile,pecoff
Platform: UNKNOWN
Classifier: Development Status :: 5 - Production/Stable
Classifier: Intended Audience :: Developers
Classifier: Intended Audience :: Science/Research
Classifier: Natural Language :: English
Classifier: Operating System :: OS Independent
Classifier: Programming Language :: Python
Classifier: Topic :: Software Development :: Libraries :: Python Modules
Requires-Dist: future
